vpx/__init__.py
vpx/auth.py
vpx/cli.py
vpx/commands/__init__.py
vpx/diann/agent.py
vpx/diann/helper_agents.py
vpx/diann/tools.py
vpx/diann/utility.py
vpx/gui/__init__.py
vpx/gui/debug_window.py
vpx/gui/launcher.py
vpx/gui/rtl_visualizer.py
vpx/secretload.py
vpx-0.1.27.dist-info/METADATA
vpx-0.1.27.dist-info/WHEEL
vpx-0.1.27.dist-info/entry_points.txt
vpx-0.1.27.dist-info/RECORD
