Metadata-Version: 2.1
Name: vpx
Version: 0.1.27
Summary: VPM with integrated agents
Author: Instachip
Author-email: team@getinstachip.com
Requires-Python: >=3.10,<4.0
Classifier: Operating System :: OS Independent
Classifier: Programming Language :: Python :: 3
Classifier: Programming Language :: Python :: 3.10
Classifier: Programming Language :: Python :: 3.11
Classifier: Programming Language :: Python :: 3.12
Classifier: Programming Language :: Python :: 3.13
Requires-Dist: anthropic
Requires-Dist: cairosvg
Requires-Dist: colorama
Requires-Dist: networkx (>=3.4.2,<4.0.0)
Requires-Dist: openai
Requires-Dist: pillow
Requires-Dist: python-dotenv (>=1.0.1,<2.0.0)
Requires-Dist: requests
Requires-Dist: svgwrite (>=1.4.3,<2.0.0)
Requires-Dist: typer (>=0.13.0,<0.14.0)
Requires-Dist: vcd
